MANIFEST.in
README.rst
setup.py
spot.py
fixtures/dotcloud.yml
fixtures/environment.json
spot.egg-info/PKG-INFO
spot.egg-info/SOURCES.txt
spot.egg-info/dependency_links.txt
spot.egg-info/requires.txt
spot.egg-info/top_level.txt