Metadata-Version: 1.0
Name: spot
Version: 0.1a
Summary: DotCloud environment loader
Home-page: http://github.com/3kwa/spot
Author: Eugene Van den Bulke
Author-email: eugene.vandenbulke@gmail.com
License: MIT
Platform: UNKNOWN
Classifier: Development Status :: 3 - Alpha
Classifier: Environment :: Web Environment
Classifier: Intended Audience :: Developers
Classifier: License :: Freely Distributable
Classifier: Operating System :: OS Independent
Classifier: Programming Language :: Python
